cli/Utils.py
cli/__init__.py
cli/Stratos.py
cli/Logging.py
cli/Configs.py
cli/CLI.py
cli/Main.py
stratos-1.0.dist-info/RECORD
stratos-1.0.dist-info/pbr.json
stratos-1.0.dist-info/entry_points.txt
stratos-1.0.dist-info/WHEEL
stratos-1.0.dist-info/top_level.txt
stratos-1.0.dist-info/METADATA
stratos-1.0.dist-info/metadata.json
stratos-1.0.dist-info/DESCRIPTION.rst
