Metadata-Version: 2.0
Name: stratos
Version: 1.0
Summary: CLI tool to interact with Apache Stratos
Home-page: http://stratos.apache.org/
Author: Apache Stratos
Author-email: dev@stratos.apache.org
License: UNKNOWN
Keywords: stratos
Platform: UNKNOWN
Classifier: Development Status :: 1 - Planning
Classifier: Topic :: Utilities
Classifier: License :: OSI Approved :: Apache Software License
Requires-Dist: cmd2
Requires-Dist: requests
Requires-Dist: texttable
